vmklib/__init__.py
vmklib/__main__.py
vmklib/app.py
vmklib/dev_requirements.txt
vmklib/entry.py
vmklib/py.typed
vmklib/requirements.txt
vmklib/util.py
vmklib/data/conf.mk
vmklib/data/datazen.mk
vmklib/data/functions.mk
vmklib/data/grip.mk
vmklib/data/python.mk
vmklib/data/time.mk
vmklib/data/venv.mk
vmklib/data/vmklib.mk
vmklib/data/yaml.mk
vmklib/data/data/edit_venv.txt
vmklib/data/data/fresh_venv.txt
vmklib/data/data/header.mk
vmklib/data/lib_tasks/__init__.py
vmklib/data/lib_tasks/conf.py
vmklib/data/lib_tasks/__pycache__/conf.cpython-313.pyc
vmklib/data/python/build.mk
vmklib/data/python/docs.mk
vmklib/data/python/pypi.mk
vmklib/data/python/upload.mk
vmklib/tasks/__init__.py
vmklib/tasks/args.py
vmklib/tasks/clean.py
vmklib/tasks/github.py
vmklib/tasks/release.py
vmklib/tasks/venv.py
vmklib/tasks/mixins/__init__.py
vmklib/tasks/mixins/concrete.py
vmklib/tasks/mixins/curl.py
vmklib/tasks/node/__init__.py
vmklib/tasks/python/__init__.py
vmklib/tasks/python/build.py
vmklib/tasks/python/datazen.py
vmklib/tasks/python/docs.py
vmklib/tasks/python/lint.py
vmklib/tasks/python/package.py
vmklib/tasks/python/release.py
vmklib/tasks/python/sa.py
vmklib/tasks/python/test.py
vmklib/tasks/python/yaml.py
vmklib-2.0.8.dist-info/licenses/LICENSE
vmklib-2.0.8.dist-info/METADATA
vmklib-2.0.8.dist-info/WHEEL
vmklib-2.0.8.dist-info/entry_points.txt
vmklib-2.0.8.dist-info/top_level.txt
vmklib-2.0.8.dist-info/RECORD
