Metadata-Version: 2.4
Name: vmklib
Version: 2.0.8
Summary: Simplify project workflows by standardizing use of GNU Make.
Home-page: https://github.com/libre-embedded/vmklib
Author: Libre Embedded
Author-email: Libre Embedded <vaughn@libre-embedded.com>
Maintainer-email: Libre Embedded <vaughn@libre-embedded.com>
License-Expression: MIT
Keywords: workflow,tool,make
Classifier: Topic :: Software Development :: Build Tools
Classifier: Programming Language :: Python :: 3.12
Classifier: Programming Language :: Python :: 3.13
Classifier: Operating System :: Microsoft :: Windows
Classifier: Operating System :: MacOS
Classifier: Operating System :: POSIX :: Linux
Classifier: Operating System :: Unix
Classifier: Development Status :: 5 - Production/Stable
Requires-Python: >=3.12
License-File: LICENSE
Requires-Dist: vcorelib>=3.4.3
Requires-Dist: experimental-lowqa
Provides-Extra: test
Requires-Dist: pylint; extra == "test"
Requires-Dist: flake8; extra == "test"
Requires-Dist: black; extra == "test"
Requires-Dist: ruff; extra == "test"
Requires-Dist: mypy; extra == "test"
Requires-Dist: isort; extra == "test"
Requires-Dist: yamllint; extra == "test"
Requires-Dist: yambs; extra == "test"
Requires-Dist: vmklib>=2.0.3; extra == "test"
Requires-Dist: sphinx; extra == "test"
Requires-Dist: sphinx-book-theme; extra == "test"
Requires-Dist: pytest-asyncio; extra == "test"
Requires-Dist: setuptools-wrapper; extra == "test"
Dynamic: author
Dynamic: home-page
Dynamic: license-file
Dynamic: requires-dist
Dynamic: requires-python
